table_partitionare/__init__.py
table_partitionare/src/__init__.py
table_partitionare/src/funcs.py
table_partitionare/src/help_funcs.py
table_partitionare/src/partition_db.py
table_partitionare/src/utils.py
table_partitionare-1.0.0.dist-info/LICENSE.txt
table_partitionare-1.0.0.dist-info/METADATA
table_partitionare-1.0.0.dist-info/WHEEL
table_partitionare-1.0.0.dist-info/top_level.txt
table_partitionare-1.0.0.dist-info/RECORD
