Metadata-Version: 2.1
Name: table-partitionare
Version: 1.0.0
Summary: A library for partitioning PostgreSQL tables
Home-page: https://github.com/ehsansam90/TablePartitionare
Author: Ehsan S.Mohammadi
Author-email: "Ehsan S. Mohammadi" <ehsannsam@gmail.com>
License: MIT
Classifier: Programming Language :: Python :: 3
Classifier: License :: OSI Approved :: MIT License
Classifier: Operating System :: OS Independent
Requires-Python: >=3.6
License-File: LICENSE.txt
Requires-Dist: greenlet==3.1.1
Requires-Dist: psycopg2-binary
Requires-Dist: python-dotenv
Requires-Dist: SQLAlchemy
